fastlens/__init__.py
fastlens/fftlog.py
fastlens/mag_fft.py
fastlens/timeave.py
fastlens-1.0.5.dist-info/LICENSE
fastlens-1.0.5.dist-info/METADATA
fastlens-1.0.5.dist-info/WHEEL
fastlens-1.0.5.dist-info/top_level.txt
fastlens-1.0.5.dist-info/RECORD
