Metadata-Version: 2.1
Name: fastlens
Version: 1.0.5
Summary: fft based microlensing package
Home-page: https://github.com/git-sunao/fft-extended-source
Author: Sunao Sugiyama
Author-email: sunaosugiyama@gmail.com
Keywords: microlensing,fft
Classifier: Development Status :: 5 - Production/Stable
Classifier: Programming Language :: Python
Classifier: Intended Audience :: Science/Research
Classifier: Programming Language :: Python :: 2
Classifier: Programming Language :: Python :: 3
License-File: LICENSE
Requires-Dist: numpy
Requires-Dist: scipy
